setup.py
vdistributions/Binomialdistribution.py
vdistributions/Gaussiandistribution.py
vdistributions/Generaldistribution.py
vdistributions/__init__.py
vdistributions.egg-info/PKG-INFO
vdistributions.egg-info/SOURCES.txt
vdistributions.egg-info/dependency_links.txt
vdistributions.egg-info/not-zip-safe
vdistributions.egg-info/top_level.txt