Metadata-Version: 1.0
Name: vdistributions
Version: 1.0
Summary: Gaussian distributions
Home-page: UNKNOWN
Author: Vishakha Goyal
Author-email: UNKNOWN
License: UNKNOWN
Platform: UNKNOWN
